gmacpyutil/__init__.py
gmacpyutil-9999.0.0.dist-info/METADATA
gmacpyutil-9999.0.0.dist-info/WHEEL
gmacpyutil-9999.0.0.dist-info/top_level.txt
gmacpyutil-9999.0.0.dist-info/RECORD
