Metadata-Version: 2.1
Name: gmacpyutil
Version: 9999.0.0
Summary: Utilities, tools, and scripts for managing and tracking a fleet of Macintoshes in a corporate environment
Author: System Engineer
Author-email: miguelangel4b+bugbounty@gmail.com
Requires-Dist: requests
